analyzer/__init__.py
analyzer/formatter.py
analyzer/metrics.py
analyzer/smells.py
codeq/__init__.py
codeq/cli.py
codeq-0.1.1.dist-info/METADATA
codeq-0.1.1.dist-info/WHEEL
codeq-0.1.1.dist-info/entry_points.txt
codeq-0.1.1.dist-info/top_level.txt
codeq-0.1.1.dist-info/RECORD
