Metadata-Version: 2.4
Name: codeq
Version: 0.1.1
Summary: CLI tool for Python code quality metrics and smell detection
Author: Ashwin Joshi
Requires-Python: >=3.7
Requires-Dist: click
Requires-Dist: radon
Requires-Dist: rich
Dynamic: author
Dynamic: requires-dist
Dynamic: requires-python
Dynamic: summary
